datasette_publish_now/__init__.py
datasette_publish_now-0.6.dist-info/LICENSE
datasette_publish_now-0.6.dist-info/METADATA
datasette_publish_now-0.6.dist-info/WHEEL
datasette_publish_now-0.6.dist-info/entry_points.txt
datasette_publish_now-0.6.dist-info/top_level.txt
datasette_publish_now-0.6.dist-info/RECORD
