Metadata-Version: 2.1
Name: datasette-publish-now
Version: 0.6
Summary: Datasette plugin for publishing data using Vercel
Home-page: https://github.com/simonw/datasette-publish-now
Author: Simon Willison
License: Apache License, Version 2.0
Platform: UNKNOWN
Requires-Dist: datasette (>=0.44)
Provides-Extra: test
Requires-Dist: pytest ; extra == 'test'
